SC_Editor/__init__.py
SC_Editor/__main__.py
SC_Editor/adb_handler.py
SC_Editor/config_manager.py
SC_Editor/csv_handler.py
SC_Editor/feature_handler.py
SC_Editor/game_data_getter.py
SC_Editor/helper.py
SC_Editor/item.py
SC_Editor/locale_handler.py
SC_Editor/managed_item.py
SC_Editor/parse_save.py
SC_Editor/patcher.py
SC_Editor/py.typed
SC_Editor/root_handler.py
SC_Editor/serialise_save.py
SC_Editor/server_handler.py
SC_Editor/updater.py
SC_Editor/user_info.py
SC_Editor/user_input_handler.py
SC_Editor/edits/__init__.py
SC_Editor/edits/basic/__init__.py
SC_Editor/edits/basic/basic_items.py
SC_Editor/edits/basic/catfruit.py
SC_Editor/edits/basic/catseyes.py
SC_Editor/edits/basic/ototo_base_mats.py
SC_Editor/edits/basic/talent_orbs.py
SC_Editor/edits/basic/talent_orbs_new.py
SC_Editor/edits/cats/__init__.py
SC_Editor/edits/cats/cat_helper.py
SC_Editor/edits/cats/cat_id_selector.py
SC_Editor/edits/cats/chara_drop.py
SC_Editor/edits/cats/clear_cat_guide.py
SC_Editor/edits/cats/evolve_cats.py
SC_Editor/edits/cats/get_remove_cats.py
SC_Editor/edits/cats/talents.py
SC_Editor/edits/cats/upgrade_blue.py
SC_Editor/edits/cats/upgrade_cats.py
SC_Editor/edits/gamototo/__init__.py
SC_Editor/edits/gamototo/fix_gamatoto.py
SC_Editor/edits/gamototo/gamatoto_xp.py
SC_Editor/edits/gamototo/helpers.py
SC_Editor/edits/gamototo/ototo_cat_cannon.py
SC_Editor/edits/levels/__init__.py
SC_Editor/edits/levels/aku.py
SC_Editor/edits/levels/allow_filibuster_clearing.py
SC_Editor/edits/levels/behemoth_culling.py
SC_Editor/edits/levels/clear_tutorial.py
SC_Editor/edits/levels/enigma_stages.py
SC_Editor/edits/levels/event_stages.py
SC_Editor/edits/levels/gauntlet.py
SC_Editor/edits/levels/itf_timed_scores.py
SC_Editor/edits/levels/legend_quest.py
SC_Editor/edits/levels/main_story.py
SC_Editor/edits/levels/outbreaks.py
SC_Editor/edits/levels/story_level_id_selector.py
SC_Editor/edits/levels/towers.py
SC_Editor/edits/levels/treasures.py
SC_Editor/edits/levels/uncanny.py
sc_editor-0.85.dist-info/LICENSE
sc_editor-0.85.dist-info/METADATA
sc_editor-0.85.dist-info/WHEEL
sc_editor-0.85.dist-info/top_level.txt
sc_editor-0.85.dist-info/RECORD
